{"MODES":{"month":{"summary":[{"proc":"레이저","sub":null,"cnt":0,"area":12681,"base":570960,"run":238490,"rate":41.8,"plan_down":165320,"op_loss":5630,"eq_loss":28820,"eq_fail":132700},{"proc":"동도금","sub":null,"cnt":0,"area":62528.2,"base":288000,"run":82756,"rate":28.7,"plan_down":177973,"op_loss":11705,"eq_loss":14111,"eq_fail":1455},{"proc":"노광","sub":null,"cnt":0,"area":44997.4,"base":629280,"run":135770,"rate":21.6,"plan_down":354400,"op_loss":118805,"eq_loss":15140,"eq_fail":5165},{"proc":"회로","sub":null,"cnt":0,"area":68978.8,"base":287280,"run":115474,"rate":40.2,"plan_down":138510,"op_loss":21570,"eq_loss":10410,"eq_fail":1316},{"proc":"AOI","sub":null,"cnt":0,"area":49072.4,"base":784800,"run":352397,"rate":44.9,"plan_down":408484,"op_loss":10755,"eq_loss":12121,"eq_fail":1043},{"proc":"수가접","sub":null,"cnt":0,"area":20695.3,"base":426240,"run":175650,"rate":41.2,"plan_down":137640,"op_loss":104710,"eq_loss":5720,"eq_fail":2520},{"proc":"적층","sub":null,"cnt":0,"area":40097.3,"base":1322640,"run":582905,"rate":44.1,"plan_down":156095,"op_loss":525320,"eq_loss":18920,"eq_fail":39400},{"proc":"가이드","sub":null,"cnt":0,"area":27846.1,"base":411840,"run":211584,"rate":51.4,"plan_down":64470,"op_loss":122470,"eq_loss":7206,"eq_fail":6110},{"proc":"금도금","sub":null,"cnt":0,"area":78746,"base":257040,"run":221560,"rate":86.2,"plan_down":17610,"op_loss":14470,"eq_loss":1080,"eq_fail":2320},{"proc":"자동가접","sub":null,"cnt":0,"area":16991.2,"base":502560,"run":351886,"rate":70,"plan_down":112210,"op_loss":6150,"eq_loss":18879,"eq_fail":13435},{"proc":"SUB","sub":null,"cnt":0,"area":3303.7,"base":136800,"run":52330,"rate":38.3,"plan_down":80400,"op_loss":1040,"eq_loss":3010,"eq_fail":20},{"proc":"BBT","sub":null,"cnt":0,"area":15608.7,"base":440640,"run":263919,"rate":59.9,"plan_down":164515,"op_loss":5075,"eq_loss":3834,"eq_fail":3297},{"proc":"타발","sub":null,"cnt":0,"area":87848.1,"base":1101600,"run":746996,"rate":67.8,"plan_down":239400,"op_loss":78050,"eq_loss":31044,"eq_fail":6110}],"detail":[{"proc":"레이저","sub":"RTR","cnt":10,"area":10581.8,"base":366480,"run":188120,"rate":51.3,"plan_down":60570,"op_loss":4330,"eq_loss":24030,"eq_fail":89430},{"proc":"레이저","sub":"SHEET","cnt":3,"area":1300.1,"base":105840,"run":32865,"rate":31.1,"plan_down":37490,"op_loss":810,"eq_loss":2960,"eq_fail":31715},{"proc":"레이저","sub":"기타(QR / COV)","cnt":3,"area":799.2,"base":98640,"run":17505,"rate":17.7,"plan_down":67260,"op_loss":490,"eq_loss":1830,"eq_fail":11555},{"proc":"동도금","sub":"블랙홀","cnt":1,"area":13765.5,"base":36720,"run":15726,"rate":42.8,"plan_down":14620,"op_loss":3005,"eq_loss":3163,"eq_fail":206},{"proc":"동도금","sub":"디스미어","cnt":1,"area":4181.7,"base":36720,"run":3408,"rate":9.3,"plan_down":28053,"op_loss":1915,"eq_loss":3194,"eq_fail":150},{"proc":"동도금","sub":"화학동","cnt":1,"area":3527.9,"base":36000,"run":2880,"rate":8,"plan_down":25950,"op_loss":2610,"eq_loss":4440,"eq_fail":120},{"proc":"동도금","sub":"SHEET 전기동","cnt":2,"area":6534,"base":36720,"run":14832,"rate":40.4,"plan_down":16355,"op_loss":3920,"eq_loss":1407,"eq_fail":206},{"proc":"동도금","sub":"RTR 전기동","cnt":1,"area":12456.7,"base":36720,"run":27887,"rate":75.9,"plan_down":6270,"op_loss":255,"eq_loss":1907,"eq_fail":401},{"proc":"동도금","sub":"BAKING","cnt":2,"area":21686.1,"base":73440,"run":17343,"rate":23.6,"plan_down":55725,"op_loss":0,"eq_loss":0,"eq_fail":372},{"proc":"동도금","sub":"ULTRA","cnt":1,"area":376.2,"base":31680,"run":680,"rate":2.1,"plan_down":31000,"op_loss":0,"eq_loss":0,"eq_fail":0},{"proc":"노광","sub":"D/F","cnt":10,"area":23804,"base":326160,"run":50217,"rate":15.4,"plan_down":202870,"op_loss":67958,"eq_loss":4510,"eq_fail":605},{"proc":"노광","sub":"MANUAL 노광","cnt":2,"area":65,"base":61920,"run":425,"rate":0.7,"plan_down":58620,"op_loss":2835,"eq_loss":40,"eq_fail":0},{"proc":"노광","sub":"RTR LDI","cnt":1,"area":1910.5,"base":33840,"run":8010,"rate":23.7,"plan_down":14530,"op_loss":10450,"eq_loss":810,"eq_fail":40},{"proc":"노광","sub":"RTR 노광","cnt":2,"area":9117.5,"base":72000,"run":34168,"rate":47.5,"plan_down":14510,"op_loss":15392,"eq_loss":6670,"eq_fail":1260},{"proc":"노광","sub":"LDI","cnt":4,"area":10100.5,"base":135360,"run":42950,"rate":31.7,"plan_down":63870,"op_loss":22170,"eq_loss":3110,"eq_fail":3260},{"proc":"회로","sub":"H/F","cnt":1,"area":6815.4,"base":34560,"run":11803,"rate":34.2,"plan_down":19230,"op_loss":2340,"eq_loss":1080,"eq_fail":107},{"proc":"회로","sub":"S/E","cnt":2,"area":24121.7,"base":73440,"run":38581,"rate":52.5,"plan_down":26350,"op_loss":5940,"eq_loss":2160,"eq_fail":409},{"proc":"회로","sub":"CZ","cnt":1,"area":7844.9,"base":36720,"run":14633,"rate":39.9,"plan_down":17950,"op_loss":2880,"eq_loss":1080,"eq_fail":177},{"proc":"회로","sub":"옥사이드","cnt":1,"area":5356.2,"base":34560,"run":10463,"rate":30.3,"plan_down":20210,"op_loss":2700,"eq_loss":1080,"eq_fail":107},{"proc":"회로","sub":"ULTRA","cnt":1,"area":2002.3,"base":36720,"run":5608,"rate":15.3,"plan_down":27860,"op_loss":2160,"eq_loss":960,"eq_fail":132},{"proc":"회로","sub":"DES","cnt":2,"area":22838.4,"base":71280,"run":34386,"rate":48.2,"plan_down":26910,"op_loss":5550,"eq_loss":4050,"eq_fail":384},{"proc":"AOI","sub":"RTR AOI","cnt":1,"area":10847.3,"base":36720,"run":18934,"rate":51.6,"plan_down":15715,"op_loss":765,"eq_loss":1269,"eq_fail":37},{"proc":"AOI","sub":"RTR VRS","cnt":2,"area":9058.7,"base":72720,"run":45175,"rate":62.1,"plan_down":24107,"op_loss":1455,"eq_loss":1359,"eq_fail":624},{"proc":"AOI","sub":"SHEET AOI","cnt":6,"area":7360.1,"base":205200,"run":101398,"rate":49.4,"plan_down":95530,"op_loss":2865,"eq_loss":5296,"eq_fail":111},{"proc":"AOI","sub":"SHEET VRS","cnt":12,"area":9938.9,"base":398160,"run":154844,"rate":38.9,"plan_down":236060,"op_loss":4470,"eq_loss":2577,"eq_fail":209},{"proc":"AOI","sub":"Vision Cut","cnt":1,"area":11716.9,"base":36720,"run":28782,"rate":78.4,"plan_down":5840,"op_loss":765,"eq_loss":1296,"eq_fail":37},{"proc":"AOI","sub":"AOS","cnt":1,"area":150.6,"base":35280,"run":3264,"rate":9.3,"plan_down":31232,"op_loss":435,"eq_loss":324,"eq_fail":25},{"proc":"수가접","sub":"Q/PRESS","cnt":6,"area":14165.6,"base":215280,"run":107395,"rate":49.9,"plan_down":55920,"op_loss":48270,"eq_loss":3615,"eq_fail":80},{"proc":"수가접","sub":"자동 EMI","cnt":2,"area":3763.3,"base":71280,"run":32400,"rate":45.5,"plan_down":18290,"op_loss":18190,"eq_loss":970,"eq_fail":1430},{"proc":"수가접","sub":"자동 COV","cnt":4,"area":2766.4,"base":139680,"run":35855,"rate":25.7,"plan_down":63430,"op_loss":38250,"eq_loss":1135,"eq_fail":1010},{"proc":"적층","sub":"H/P","cnt":38,"area":40097.3,"base":1322640,"run":582905,"rate":44.1,"plan_down":156095,"op_loss":525320,"eq_loss":18920,"eq_fail":39400},{"proc":"가이드","sub":"X-RAY","cnt":1,"area":3045,"base":36000,"run":10985,"rate":30.5,"plan_down":8160,"op_loss":16275,"eq_loss":555,"eq_fail":25},{"proc":"가이드","sub":"RTR GUIDE","cnt":1,"area":7166.1,"base":36720,"run":16925,"rate":46.1,"plan_down":6300,"op_loss":6030,"eq_loss":1600,"eq_fail":5865},{"proc":"가이드","sub":"자동 GUIDE","cnt":10,"area":17635,"base":339120,"run":183674,"rate":54.2,"plan_down":50010,"op_loss":100165,"eq_loss":5051,"eq_fail":220},{"proc":"금도금","sub":"JET LINE","cnt":1,"area":13606,"base":36720,"run":33970,"rate":92.5,"plan_down":600,"op_loss":1810,"eq_loss":120,"eq_fail":220},{"proc":"금도금","sub":"LINE E.N.I.G","cnt":1,"area":13606,"base":36720,"run":31690,"rate":86.3,"plan_down":600,"op_loss":1910,"eq_loss":960,"eq_fail":1560},{"proc":"금도금","sub":"ULTRA","cnt":1,"area":13606,"base":36720,"run":31690,"rate":86.3,"plan_down":600,"op_loss":4340,"eq_loss":0,"eq_fail":90},{"proc":"금도금","sub":"X-RAY","cnt":1,"area":13605,"base":36720,"run":31690,"rate":86.3,"plan_down":600,"op_loss":4340,"eq_loss":0,"eq_fail":90},{"proc":"금도금","sub":"플라즈마","cnt":3,"area":24323,"base":110160,"run":92520,"rate":84,"plan_down":15210,"op_loss":2070,"eq_loss":0,"eq_fail":360},{"proc":"자동가접","sub":"Q/PRESS","cnt":3,"area":2992.6,"base":104400,"run":58742,"rate":56.3,"plan_down":42970,"op_loss":1050,"eq_loss":1598,"eq_fail":40},{"proc":"자동가접","sub":"DAWON","cnt":4,"area":1818,"base":141120,"run":99284,"rate":70.4,"plan_down":33380,"op_loss":1880,"eq_loss":6496,"eq_fail":80},{"proc":"자동가접","sub":"꿕바오","cnt":2,"area":2378.6,"base":74160,"run":65341,"rate":88.1,"plan_down":4340,"op_loss":1030,"eq_loss":3279,"eq_fail":170},{"proc":"자동가접","sub":"FAST","cnt":3,"area":3727.4,"base":110160,"run":80544,"rate":73.1,"plan_down":17980,"op_loss":1360,"eq_loss":7471,"eq_fail":2805},{"proc":"자동가접","sub":"AIR BAG","cnt":2,"area":6074.6,"base":72720,"run":47975,"rate":66,"plan_down":13540,"op_loss":830,"eq_loss":35,"eq_fail":10340},{"proc":"SUB","sub":"Q/PRESS","cnt":4,"area":3303.7,"base":136800,"run":52330,"rate":38.3,"plan_down":80400,"op_loss":1040,"eq_loss":3010,"eq_fail":20},{"proc":"BBT","sub":"수동 BBT","cnt":5,"area":1488.4,"base":172800,"run":46125,"rate":26.7,"plan_down":123645,"op_loss":1320,"eq_loss":592,"eq_fail":1118},{"proc":"BBT","sub":"AUTO BBT","cnt":9,"area":14120.2,"base":267840,"run":217794,"rate":81.3,"plan_down":40870,"op_loss":3755,"eq_loss":3242,"eq_fail":2179},{"proc":"타발","sub":"PRESS","cnt":26,"area":62711.1,"base":923040,"run":621427,"rate":67.3,"plan_down":195450,"op_loss":76930,"eq_loss":23203,"eq_fail":6030},{"proc":"타발","sub":"CUTTING","cnt":2,"area":16726.7,"base":72720,"run":55573,"rate":76.4,"plan_down":11460,"op_loss":840,"eq_loss":4807,"eq_fail":40},{"proc":"타발","sub":"보강판 PRESS","cnt":2,"area":856.3,"base":72720,"run":59316,"rate":81.6,"plan_down":11450,"op_loss":240,"eq_loss":1674,"eq_fail":40},{"proc":"타발","sub":"고속 타발","cnt":1,"area":7554,"base":33120,"run":10680,"rate":32.2,"plan_down":21040,"op_loss":40,"eq_loss":1360,"eq_fail":0}],"period":"6/1~6/26","overall":48.9},"day":{"summary":[{"proc":"레이저","sub":null,"cnt":0,"area":628.9,"base":23040,"run":8070,"rate":35,"plan_down":7420,"op_loss":160,"eq_loss":910,"eq_fail":6480},{"proc":"동도금","sub":null,"cnt":0,"area":2862.2,"base":11520,"run":3623,"rate":31.4,"plan_down":7050,"op_loss":485,"eq_loss":362,"eq_fail":0},{"proc":"노광","sub":null,"cnt":0,"area":1828.1,"base":27360,"run":6150,"rate":22.5,"plan_down":16980,"op_loss":3150,"eq_loss":1080,"eq_fail":0},{"proc":"회로","sub":null,"cnt":0,"area":3486.2,"base":11520,"run":5890,"rate":51.1,"plan_down":4650,"op_loss":900,"eq_loss":80,"eq_fail":0},{"proc":"AOI","sub":null,"cnt":0,"area":1968.2,"base":33120,"run":16423,"rate":49.6,"plan_down":15761,"op_loss":480,"eq_loss":456,"eq_fail":0},{"proc":"수가접","sub":null,"cnt":0,"area":585,"base":17280,"run":6485,"rate":37.5,"plan_down":6300,"op_loss":4270,"eq_loss":165,"eq_fail":60},{"proc":"적층","sub":null,"cnt":0,"area":1564.6,"base":54720,"run":22255,"rate":40.7,"plan_down":6620,"op_loss":23685,"eq_loss":720,"eq_fail":1440},{"proc":"가이드","sub":null,"cnt":0,"area":1144.8,"base":17280,"run":9630,"rate":55.7,"plan_down":2700,"op_loss":3240,"eq_loss":270,"eq_fail":1440},{"proc":"금도금","sub":null,"cnt":0,"area":3444,"base":10080,"run":8480,"rate":84.1,"plan_down":480,"op_loss":880,"eq_loss":240,"eq_fail":0},{"proc":"자동가접","sub":null,"cnt":0,"area":780.5,"base":20160,"run":14882,"rate":73.8,"plan_down":3510,"op_loss":260,"eq_loss":1508,"eq_fail":0},{"proc":"SUB","sub":null,"cnt":0,"area":118,"base":5760,"run":1710,"rate":29.7,"plan_down":3910,"op_loss":40,"eq_loss":100,"eq_fail":0},{"proc":"BBT","sub":null,"cnt":0,"area":716.3,"base":20160,"run":12039,"rate":59.7,"plan_down":7680,"op_loss":200,"eq_loss":166,"eq_fail":75},{"proc":"타발","sub":null,"cnt":0,"area":4013.4,"base":44640,"run":30022,"rate":67.3,"plan_down":9160,"op_loss":4050,"eq_loss":1168,"eq_fail":240}],"detail":[{"proc":"레이저","sub":"RTR","cnt":10,"area":571.5,"base":14400,"run":6940,"rate":48.2,"plan_down":2880,"op_loss":140,"eq_loss":840,"eq_fail":3600},{"proc":"레이저","sub":"SHEET","cnt":3,"area":0,"base":4320,"run":0,"rate":0,"plan_down":2880,"op_loss":0,"eq_loss":0,"eq_fail":1440},{"proc":"레이저","sub":"기타(QR / COV)","cnt":3,"area":57.4,"base":4320,"run":1130,"rate":26.2,"plan_down":1660,"op_loss":20,"eq_loss":70,"eq_fail":1440},{"proc":"동도금","sub":"블랙홀","cnt":1,"area":416.2,"base":1440,"run":475,"rate":33,"plan_down":830,"op_loss":120,"eq_loss":15,"eq_fail":0},{"proc":"동도금","sub":"디스미어","cnt":1,"area":292.1,"base":1440,"run":228,"rate":15.8,"plan_down":1100,"op_loss":90,"eq_loss":22,"eq_fail":0},{"proc":"동도금","sub":"화학동","cnt":1,"area":256.8,"base":1440,"run":210,"rate":14.6,"plan_down":850,"op_loss":115,"eq_loss":265,"eq_fail":0},{"proc":"동도금","sub":"SHEET 전기동","cnt":2,"area":370.8,"base":1440,"run":850,"rate":59,"plan_down":370,"op_loss":160,"eq_loss":60,"eq_fail":0},{"proc":"동도금","sub":"RTR 전기동","cnt":1,"area":414.5,"base":1440,"run":940,"rate":65.3,"plan_down":500,"op_loss":0,"eq_loss":0,"eq_fail":0},{"proc":"동도금","sub":"BAKING","cnt":2,"area":1095.5,"base":2880,"run":880,"rate":30.6,"plan_down":2000,"op_loss":0,"eq_loss":0,"eq_fail":0},{"proc":"동도금","sub":"ULTRA","cnt":1,"area":16.4,"base":1440,"run":40,"rate":2.8,"plan_down":1400,"op_loss":0,"eq_loss":0,"eq_fail":0},{"proc":"노광","sub":"D/F","cnt":10,"area":945.3,"base":14400,"run":2505,"rate":17.4,"plan_down":9880,"op_loss":1835,"eq_loss":180,"eq_fail":0},{"proc":"노광","sub":"MANUAL 노광","cnt":2,"area":0,"base":2880,"run":0,"rate":0,"plan_down":2880,"op_loss":0,"eq_loss":0,"eq_fail":0},{"proc":"노광","sub":"RTR LDI","cnt":1,"area":31.4,"base":1440,"run":165,"rate":11.5,"plan_down":460,"op_loss":775,"eq_loss":40,"eq_fail":0},{"proc":"노광","sub":"RTR 노광","cnt":2,"area":389.1,"base":2880,"run":1460,"rate":50.7,"plan_down":440,"op_loss":120,"eq_loss":860,"eq_fail":0},{"proc":"노광","sub":"LDI","cnt":4,"area":462.3,"base":5760,"run":2020,"rate":35.1,"plan_down":3320,"op_loss":420,"eq_loss":0,"eq_fail":0},{"proc":"회로","sub":"H/F","cnt":1,"area":596.8,"base":1440,"run":1100,"rate":76.4,"plan_down":220,"op_loss":120,"eq_loss":0,"eq_fail":0},{"proc":"회로","sub":"S/E","cnt":2,"area":1243.6,"base":2880,"run":1920,"rate":66.7,"plan_down":720,"op_loss":240,"eq_loss":0,"eq_fail":0},{"proc":"회로","sub":"CZ","cnt":1,"area":359.3,"base":1440,"run":610,"rate":42.4,"plan_down":710,"op_loss":120,"eq_loss":0,"eq_fail":0},{"proc":"회로","sub":"옥사이드","cnt":1,"area":287.9,"base":1440,"run":520,"rate":36.1,"plan_down":800,"op_loss":120,"eq_loss":0,"eq_fail":0},{"proc":"회로","sub":"ULTRA","cnt":1,"area":59.2,"base":1440,"run":180,"rate":12.5,"plan_down":1200,"op_loss":60,"eq_loss":0,"eq_fail":0},{"proc":"회로","sub":"DES","cnt":2,"area":939.4,"base":2880,"run":1560,"rate":54.2,"plan_down":1000,"op_loss":240,"eq_loss":80,"eq_fail":0},{"proc":"AOI","sub":"RTR AOI","cnt":1,"area":407,"base":1440,"run":829,"rate":57.6,"plan_down":560,"op_loss":30,"eq_loss":21,"eq_fail":0},{"proc":"AOI","sub":"RTR VRS","cnt":2,"area":238.8,"base":2880,"run":1033,"rate":35.9,"plan_down":1760,"op_loss":60,"eq_loss":27,"eq_fail":0},{"proc":"AOI","sub":"SHEET AOI","cnt":6,"area":320,"base":8640,"run":4517,"rate":52.3,"plan_down":3760,"op_loss":120,"eq_loss":243,"eq_fail":0},{"proc":"AOI","sub":"SHEET VRS","cnt":12,"area":576.2,"base":17280,"run":8802,"rate":50.9,"plan_down":8130,"op_loss":225,"eq_loss":123,"eq_fail":0},{"proc":"AOI","sub":"Vision Cut","cnt":1,"area":420,"base":1440,"run":1160,"rate":80.6,"plan_down":220,"op_loss":30,"eq_loss":30,"eq_fail":0},{"proc":"AOI","sub":"AOS","cnt":1,"area":6.2,"base":1440,"run":82,"rate":5.7,"plan_down":1331,"op_loss":15,"eq_loss":12,"eq_fail":0},{"proc":"수가접","sub":"Q/PRESS","cnt":6,"area":369.7,"base":8640,"run":3685,"rate":42.7,"plan_down":2540,"op_loss":2310,"eq_loss":105,"eq_fail":0},{"proc":"수가접","sub":"자동 EMI","cnt":2,"area":176,"base":2880,"run":1720,"rate":59.7,"plan_down":440,"op_loss":640,"eq_loss":40,"eq_fail":40},{"proc":"수가접","sub":"자동 COV","cnt":4,"area":39.3,"base":5760,"run":1080,"rate":18.8,"plan_down":3320,"op_loss":1320,"eq_loss":20,"eq_fail":20},{"proc":"적층","sub":"H/P","cnt":38,"area":1564.6,"base":54720,"run":22255,"rate":40.7,"plan_down":6620,"op_loss":23685,"eq_loss":720,"eq_fail":1440},{"proc":"가이드","sub":"X-RAY","cnt":1,"area":309.2,"base":1440,"run":990,"rate":68.8,"plan_down":220,"op_loss":200,"eq_loss":30,"eq_fail":0},{"proc":"가이드","sub":"RTR GUIDE","cnt":1,"area":0,"base":1440,"run":0,"rate":0,"plan_down":0,"op_loss":0,"eq_loss":0,"eq_fail":1440},{"proc":"가이드","sub":"자동 GUIDE","cnt":10,"area":835.6,"base":14400,"run":8640,"rate":60,"plan_down":2480,"op_loss":3040,"eq_loss":240,"eq_fail":0},{"proc":"금도금","sub":"JET LINE","cnt":1,"area":623,"base":1440,"run":1370,"rate":95.1,"plan_down":0,"op_loss":70,"eq_loss":0,"eq_fail":0},{"proc":"금도금","sub":"LINE E.N.I.G","cnt":1,"area":623,"base":1440,"run":1130,"rate":78.5,"plan_down":0,"op_loss":70,"eq_loss":240,"eq_fail":0},{"proc":"금도금","sub":"ULTRA","cnt":1,"area":623,"base":1440,"run":1130,"rate":78.5,"plan_down":0,"op_loss":310,"eq_loss":0,"eq_fail":0},{"proc":"금도금","sub":"X-RAY","cnt":1,"area":623,"base":1440,"run":1130,"rate":78.5,"plan_down":0,"op_loss":310,"eq_loss":0,"eq_fail":0},{"proc":"금도금","sub":"플라즈마","cnt":3,"area":952,"base":4320,"run":3720,"rate":86.1,"plan_down":480,"op_loss":120,"eq_loss":0,"eq_fail":0},{"proc":"자동가접","sub":"Q/PRESS","cnt":3,"area":167.9,"base":4320,"run":2918,"rate":67.5,"plan_down":1270,"op_loss":50,"eq_loss":82,"eq_fail":0},{"proc":"자동가접","sub":"DAWON","cnt":4,"area":82.7,"base":5760,"run":4023,"rate":69.8,"plan_down":1000,"op_loss":80,"eq_loss":657,"eq_fail":0},{"proc":"자동가접","sub":"꿕바오","cnt":2,"area":120,"base":2880,"run":2660,"rate":92.4,"plan_down":80,"op_loss":40,"eq_loss":100,"eq_fail":0},{"proc":"자동가접","sub":"FAST","cnt":3,"area":130.8,"base":4320,"run":2881,"rate":66.7,"plan_down":720,"op_loss":50,"eq_loss":669,"eq_fail":0},{"proc":"자동가접","sub":"AIR BAG","cnt":2,"area":279.2,"base":2880,"run":2400,"rate":83.3,"plan_down":440,"op_loss":40,"eq_loss":0,"eq_fail":0},{"proc":"SUB","sub":"Q/PRESS","cnt":4,"area":118,"base":5760,"run":1710,"rate":29.7,"plan_down":3910,"op_loss":40,"eq_loss":100,"eq_fail":0},{"proc":"BBT","sub":"수동 BBT","cnt":5,"area":27.1,"base":7200,"run":560,"rate":7.8,"plan_down":6600,"op_loss":20,"eq_loss":2,"eq_fail":18},{"proc":"BBT","sub":"AUTO BBT","cnt":9,"area":689.1,"base":12960,"run":11479,"rate":88.6,"plan_down":1080,"op_loss":180,"eq_loss":164,"eq_fail":57},{"proc":"타발","sub":"PRESS","cnt":26,"area":3274.9,"base":37440,"run":25394,"rate":67.8,"plan_down":7560,"op_loss":3330,"eq_loss":916,"eq_fail":240},{"proc":"타발","sub":"CUTTING","cnt":2,"area":318.2,"base":2880,"run":1696,"rate":58.9,"plan_down":330,"op_loss":720,"eq_loss":134,"eq_fail":0},{"proc":"타발","sub":"보강판 PRESS","cnt":2,"area":34.4,"base":2880,"run":2394,"rate":83.1,"plan_down":440,"op_loss":0,"eq_loss":46,"eq_fail":0},{"proc":"타발","sub":"고속 타발","cnt":1,"area":386,"base":1440,"run":538,"rate":37.4,"plan_down":830,"op_loss":0,"eq_loss":72,"eq_fail":0}],"period":"6/26","overall":49.1}},"TREND":{"레이저":[53.2,39.5,40.6,40.6,45.4,41.8],"동도금":[31.4,20.6,25.5,17.1,29.4,28.7],"노광":[21,15.1,15.9,14.4,21.4,21.6],"회로":[29.7,20.4,26.1,28.8,37.4,40.2],"AOI":[49.7,33.5,37.4,37.8,51.6,44.9],"수가접":[54,39.3,49.2,41.9,46.4,41.2],"적층":[54.5,33.1,39.6,35.3,41.2,44.1],"가이드":[50.9,31.3,45.7,39,49,51.4],"금도금":[80.2,52,75.6,70.5,82.1,86.2],"자동가접":[64.6,56.8,66.5,45.2,60.7,70],"SUB":[36.3,25.2,47.7,37.7,37.8,38.3],"BBT":[39,30.3,41.4,39.8,45.5,59.9],"타발":[63,40.7,47.5,53.8,64.4,67.8]},"ETRD":{"레이저_RTR":[72,51.1,50,48,58.3,51.3],"레이저_SHEET":[37.1,33.2,39.9,43.2,26.7,31.1],"레이저_기타(QR / COV)":[29.9,19.4,16.4,13.3,14.8,17.7],"동도금_블랙홀":[51.8,35,39.5,31.4,44.2,42.8],"동도금_디스미어":[13.4,3.1,9.8,5,11.7,9.3],"동도금_화학동":[5.4,3.8,9.3,3.3,9.7,8],"동도금_SHEET 전기동":[51.2,24.6,35.8,25.2,45.1,40.4],"동도금_RTR 전기동":[61.5,51.6,55.8,46.3,68.3,75.9],"동도금_BAKING":[31.3,20.8,24.1,12.1,23.6,23.6],"동도금_ULTRA":[5.1,4.8,5.8,1.8,1.9,2.1],"노광_D/F":[12,8.6,8.4,8.9,14.3,15.4],"노광_MANUAL 노광":[2.7,1.8,2.1,1.2,1.1,0.7],"노광_RTR LDI":[5.9,2.4,2.9,12.4,16.6,23.7],"노광_RTR 노광":[21.6,13.9,5.2,19.4,24.7,47.5],"노광_LDI":[56.2,42,50.2,32.6,45,31.7],"회로_H/F":[50.6,27.7,19.3,32.6,43.6,34.2],"회로_S/E":[47.1,32.3,46.8,42.7,50.9,52.5],"회로_CZ":[12.1,8.4,15.6,20.7,28.9,39.9],"회로_옥사이드":[9.7,7.1,12.7,19.2,19.5,30.3],"회로_ULTRA":[3.2,1.6,4.5,8.3,12.2,15.3],"회로_DES":[34.1,26.9,31.7,32,46.1,48.2],"AOI_RTR AOI":[53.8,32.9,32.3,66.5,67.2,51.6],"AOI_RTR VRS":[45.4,28.3,16.1,44.6,65.7,62.1],"AOI_SHEET AOI":[65.4,47.3,51,45,62.7,49.4],"AOI_SHEET VRS":[44.8,29.9,39.9,31.4,44,38.9],"AOI_Vision Cut":[69,38.9,11.1,65,67.9,78.4],"AOI_AOS":[null,null,null,1.4,7.2,9.3],"수가접_Q/PRESS":[63.6,45.3,63.9,58.5,57.2,49.9],"수가접_자동 EMI":[37.6,29.3,31.9,23.5,46.7,45.5],"수가접_자동 COV":[41.8,31.1,29.2,26.3,29.6,25.7],"적층_H/P":[54.5,33.1,39.6,35.3,41.2,44.1],"가이드_X-RAY":[18.7,1.6,25.7,23.2,25.9,30.5],"가이드_RTR GUIDE":[6.9,9,6.5,16.2,39.6,46.1],"가이드_자동 GUIDE":[58.5,36.5,51.7,42.9,52.6,54.2],"금도금_JET LINE":[84.5,61.6,83.6,65.7,85,92.5],"금도금_LINE E.N.I.G":[84.2,60.4,82.2,65.7,80.2,86.3],"금도금_ULTRA":[84.2,60.4,82.6,65.7,80.2,86.3],"금도금_X-RAY":[84.2,60.1,82.6,65.7,80.2,86.3],"금도금_플라즈마":[74.7,40.5,66.1,77,83,84],"자동가접_Q/PRESS":[75.6,57,70.2,53.4,67.3,56.3],"자동가접_DAWON":[60.1,50.7,68.5,43.5,68.5,70.4],"자동가접_꿕바오":[78.4,71.3,80.1,50.3,52.3,88.1],"자동가접_FAST":[69,58.5,45.1,37.4,54.2,73.1],"자동가접_AIR BAG":[36.3,51.9,75.1,42.7,54.7,66],"SUB_Q/PRESS":[36.3,25.2,47.7,37.7,37.8,38.3],"BBT_수동 BBT":[17.8,13.7,23.3,20.9,15.4,26.7],"BBT_AUTO BBT":[70.7,55.2,68.4,68.3,78,81.3],"타발_PRESS":[63.2,39.1,47.5,53.2,65.3,67.3],"타발_CUTTING":[57.1,49.8,54.2,57.8,69.1,76.4],"타발_보강판 PRESS":[68.4,60.8,58.6,68.2,63.4,81.6],"타발_고속 타발":[60.3,23.1,12.1,31.9,29.8,32.2]},"saved":"2026-06-29T04:38:35.973Z"}